{"specialAttack":99,"specialDefense":92,"attack":77,"defense":72,"speed":58,"hp":123,"baseFriendship":0,"baseExp":104,"catchRate":45,"maleRatio":87,"pokedexId":699,"width":2.7,"height":2.7,"length":2.7,"weight":225.0,"minSpawnGroupSize":1,"maxSpawnGroupSize":1,"renderScale":[0.0,0.0,0.0],"guiScale":[0.0,0.0,0.0],"hoveringHeight":0,"eggCycles":31,"spawnInformation":{},"aggression":{},"evGain":{},"levelMoves":{},"moves":{},"tutorMoves":{},"evolutions":[],"types":["Rock","Ice"],"canFly":false,"canSurf":false,"doesHover":false,"isRideable":true,"legendary":false,"expGainSpeed":104}