{"specialAttack":90,"specialDefense":72,"attack":100,"defense":72,"speed":46,"hp":74,"baseFriendship":70,"baseExp":164,"catchRate":200,"maleRatio":50,"pokedexId":455,"width":1.0,"height":1.4,"length":1.0,"weight":27.0,"minSpawnGroupSize":1,"maxSpawnGroupSize":1,"renderScale":[0.0,0.0,0.0],"guiScale":[1.0,1.0,1.0],"hoveringHeight":0,"eggCycles":26,"spawnInformation":{},"aggression":{},"evGain":{},"levelMoves":{"11":["Vine Whip"],"1":["Bind","Growth"],"47":["Wring Out"],"37":["Spit Up","Swallow","Stockpile"],"27":["Faint Attack"],"17":["Sweet Scent"],"7":["Bite"],"50":["Power Whip"],"41":["Crunch"],"31":["Leaf Tornado"],"21":["Ingrain"]},"moves":{"egg":["Giga Drain","Magical Leaf","Slam","Worry Seed","Acid Spray","Synthesis","Stun Spore","Razor Leaf","Grass Whistle","Sleep Powder","Leech Seed","Rage Powder"],"evolution":[],"tr":["Hyper Beam","Giga Impact","Magical Leaf","Solar Beam","Rest","Thief","Snore","Protect","Giga Drain","Attract","Sunny Day","Facade","Bullet Seed","Payback","Fling","Round","Swords Dance","Substitute","Sludge Bomb","Endure","Sleep Talk","Crunch","Seed Bomb","Energy Ball","Power Whip","Grass Knot","Throat Chop"]},"tutorMoves":{"Regular":["Defog","Giga Drain","Bind","Seed Bomb","Snore","Worry Seed","Synthesis","Knock Off","Bug Bite","Gastro Acid","Throat Chop"],"Transfer":["Secret Power","Natural Gift","Confide","Cut","Hidden Power","Double Team","Infestation","Mud-Slap","Toxic","Swagger","Flash","Return","Nature Power","Captivate","Fury Cutter","Frustration"]},"evolutions":[],"types":["Grass"],"canFly":false,"canSurf":false,"doesHover":false,"isRideable":false,"legendary":false,"expGainSpeed":164}