{"specialAttack":70,"specialDefense":160,"attack":70,"defense":160,"speed":90,"hp":50,"baseFriendship":0,"baseExp":270,"catchRate":3,"maleRatio":-1,"pokedexId":386,"width":1.7,"height":1.7,"length":1.7,"weight":60.8,"minSpawnGroupSize":1,"maxSpawnGroupSize":1,"renderScale":[0.0,0.0,0.0],"guiScale":[1.0,1.0,1.0],"hoveringHeight":0,"eggCycles":121,"spawnInformation":{},"aggression":{},"evGain":{},"levelMoves":{"55":["Amnesia","Iron Defense"],"67":["Psycho Boost"],"13":["Teleport"],"25":["Spikes"],"37":["Snatch"],"49":["Zen Headbutt"],"19":["Knock Off"],"1":["Leer","Wrap"],"7":["Night Shade"],"61":["Recover"],"73":["Counter","Mirror Coat"],"31":["Psychic"],"43":["Psycho Shift"]},"moves":{"egg":["Focus Punch","Telekinesis","Bind","Snore","Stomping Tantrum","Throat Chop","Snatch","Wonder Room","Iron Defense","Ally Switch","Signal Beam","Skill Swap","Gravity","Drain Punch","Trick","Knock Off","Magic Coat","Role Play","Water Pulse","Low Kick","Stealth Rock","Recycle","Zen Headbutt","Shock Wave","Laser Focus"],"evolution":[],"tr":["Psyshock","Calm Mind","Toxic","Hidden Power","Sunny Day","Taunt","Ice Beam","Hyper Beam","Light Screen","Protect","Rain Dance","Safeguard","Frustration","Solar Beam","Thunderbolt","Thunder","Return","Psychic","Shadow Ball","Brick Break","Double Team","Reflect","Rock Tomb","Aerial Ace","Torment","Facade","Rest","Low Sweep","Round","Focus Blast","Energy Ball","Fling","Charge Beam","Brutal Swing","Giga Impact","Thunder Wave","Psych Up","Rock Slide","Poison Jab","Dream Eater","Grass Knot","Swagger","Sleep Talk","Substitute","Flash Cannon","Trick Room","Dark Pulse","Confide"]},"tutorMoves":{"Regular":["Focus Punch","Telekinesis","Bind","Snore","Stomping Tantrum","Throat Chop","Snatch","Wonder Room","Iron Defense","Ally Switch","Signal Beam","Skill Swap","Gravity","Drain Punch","Trick","Knock Off","Magic Coat","Role Play","Water Pulse","Low Kick","Stealth Rock","Recycle","Zen Headbutt","Shock Wave","Laser Focus"],"Transfer":["Rock Smash","Taunt","Secret Power","Light Screen","Dream Eater","Body Slam","Substitute","Ice Beam","Double-Edge","Thunder Wave","Cut","Hidden Power","Mega Punch","Sunny Day","Calm Mind","Rock Tomb","Double Team","Mud-Slap","Facade","Toxic","Aerial Ace","Seismic Toss","Solar Beam","Headbutt","Mega Kick","Rest","Rock Slide","Shadow Ball","Flash","Brick Break","Safeguard","Protect","Rain Dance","Thunder","Return","Mimic","Hyper Beam","Reflect","Sleep Talk","Torment","Thunderbolt","Strength","Frustration"],"Event":["Nasty Plot"]},"evolutions":[],"types":["Psychic"],"canFly":false,"canSurf":false,"doesHover":false,"isRideable":false,"legendary":false,"expGainSpeed":270}