{"specialAttack":135,"specialDefense":91,"attack":60,"defense":85,"speed":36,"hp":78,"baseFriendship":70,"baseExp":78,"catchRate":70,"maleRatio":50,"pokedexId":780,"width":3.0,"height":3.0,"length":3.0,"weight":185.0,"minSpawnGroupSize":1,"maxSpawnGroupSize":1,"renderScale":[0.0,0.0,0.0],"guiScale":[0.0,0.0,0.0],"hoveringHeight":0,"eggCycles":2,"spawnInformation":{},"aggression":{},"evGain":{},"levelMoves":{},"moves":{},"tutorMoves":{},"evolutions":[],"types":["Normal","Dragon"],"canFly":false,"canSurf":false,"doesHover":false,"isRideable":false,"legendary":false,"expGainSpeed":78}