{"specialAttack":105,"specialDefense":66,"attack":97,"defense":66,"speed":65,"hp":85,"baseFriendship":70,"baseExp":169,"catchRate":90,"maleRatio":50,"pokedexId":631,"width":1.0,"height":1.4,"length":1.0,"weight":58.0,"minSpawnGroupSize":1,"maxSpawnGroupSize":1,"renderScale":[0.0,0.0,0.0],"guiScale":[0.0,0.0,0.0],"hoveringHeight":0,"eggCycles":21,"spawnInformation":{},"aggression":{},"evGain":{},"levelMoves":{},"moves":{},"tutorMoves":{},"evolutions":[],"types":["Fire"],"canFly":false,"canSurf":false,"doesHover":false,"isRideable":false,"legendary":false,"expGainSpeed":169}