{"specialAttack":35,"specialDefense":110,"attack":105,"defense":79,"speed":76,"hp":50,"baseFriendship":70,"baseExp":140,"catchRate":45,"maleRatio":100,"pokedexId":107,"width":1.0,"height":1.4,"length":1.0,"weight":50.2,"minSpawnGroupSize":1,"maxSpawnGroupSize":1,"renderScale":[0.0,0.0,0.0],"guiScale":[0.75,0.75,0.75],"hoveringHeight":0,"eggCycles":26,"spawnInformation":{},"aggression":{},"evGain":{},"levelMoves":{"44":["Focus Punch"],"1":["Helping Hand","Drain Punch","Tackle","Focus Energy","Fake Out","Feint","Vacuum Wave","Bullet Punch"],"12":["Detect"],"24":["Thunder Punch","Fire Punch","Ice Punch"],"36":["Close Combat"],"4":["Mach Punch"],"16":["Revenge"],"28":["Agility"],"8":["Power-Up Punch"],"40":["Counter"],"32":["Mega Punch"],"21":["Quick Guard"]},"moves":{"egg":["Counter","Rapid Spin","Hi Jump Kick","Feint","Mind Reader","Vacuum Wave","Mach Punch","Bullet Punch"],"evolution":["Drain Punch"],"tr":["Snore","Facade","Uproar","Focus Energy","Metronome","Stone Edge","Retaliate","Revenge","Bulk Up","Throat Chop","Close Combat","Mega Kick","Rest","Earthquake","Work Up","Rock Slide","Agility","Aura Sphere","Round","Body Slam","Bulldoze","Substitute","Brick Break","Attract","Helping Hand","Protect","Drain Punch","Rain Dance","Mega Punch","Thief","Sunny Day","Focus Blast","Fling","Rock Tomb","Low Kick","Endure","Sleep Talk","Swift","Thunder Punch","Low Sweep","Fire Punch","Ice Punch"]},"tutorMoves":{"Regular":["Coaching"],"Transfer":["Rock Smash","Comet Punch","Secret Power","Natural Gift","Confide","Curse","Double-Edge","Leer","Take Down","Hidden Power","Dizzy Punch","Bide","Double Team","Mud-Slap","Toxic","Rock Climb","Seismic Toss","Rage","Headbutt","Dynamic Punch","Skull Bash","Swagger","Ally Switch","Return","Submission","Mimic","Captivate","Sky Uppercut","Pursuit","Role Play","Covet","Strength","Frustration","Laser Focus"]},"evolutions":[],"types":["Fighting"],"canFly":false,"canSurf":false,"doesHover":false,"isRideable":false,"legendary":false,"expGainSpeed":140}