{"specialAttack":105,"specialDefense":80,"attack":145,"defense":90,"speed":91,"hp":89,"baseFriendship":90,"baseExp":270,"catchRate":3,"maleRatio":100,"pokedexId":645,"width":1.0,"height":1.3,"length":1.0,"weight":68.0,"minSpawnGroupSize":1,"maxSpawnGroupSize":1,"renderScale":[0.0,0.0,0.0],"guiScale":[1.0,1.0,1.0],"hoveringHeight":0,"eggCycles":121,"spawnInformation":{},"aggression":{},"evGain":{},"levelMoves":{"55":["Hammer Arm"],"45":["Extrasensory"],"35":["Rock Slide"],"25":["Swords Dance"],"15":["Bulldoze"],"1":["Sand Tomb","Rock Throw"],"5":["Leer"],"70":["Outrage"],"60":["Sandstorm"],"50":["Stone Edge"],"40":["Earth Power"],"30":["Imprison"],"75":["Fissure"],"20":["Rock Tomb"],"65":["Earthquake"],"10":["Block"]},"moves":{"egg":[],"evolution":[],"tr":["Weather Ball","Snore","Facade","Sludge Bomb","Stone Edge","Grass Knot","U-turn","Swords Dance","Bulk Up","Fly","Rest","Sand Tomb","Earthquake","Iron Tail","Rock Slide","Sludge Wave","Earth Power","Scary Face","Round","Body Slam","Sandstorm","Bulldoze","Imprison","Mud Shot","Substitute","Superpower","Brick Break","Attract","Giga Impact","Payback","Protect","Dig","Self-Destruct","Hyper Beam","Focus Blast","Outrage","Calm Mind","Fling","Psychic","Rock Tomb","Brutal Swing","Endure","Sleep Talk","Stealth Rock"]},"tutorMoves":{"Transfer":["Rock Smash","Secret Power","Confide","Defog","Explosion","Hidden Power","Smack Down","Double Team","Punishment","Toxic","Swagger","Gravity","Return","Knock Off","Rock Polish","Role Play","Strength","Frustration"]},"evolutions":[],"types":["Ground","Flying"],"canFly":true,"canSurf":false,"doesHover":false,"isRideable":true,"legendary":false,"expGainSpeed":270}