{"specialAttack":50,"specialDefense":55,"attack":85,"defense":55,"speed":60,"hp":55,"baseFriendship":70,"baseExp":72,"catchRate":45,"maleRatio":50,"pokedexId":636,"width":1.0,"height":1.1,"length":1.0,"weight":28.8,"minSpawnGroupSize":1,"maxSpawnGroupSize":1,"renderScale":[0.0,0.0,0.0],"guiScale":[1.0,1.0,1.0],"hoveringHeight":0,"eggCycles":41,"spawnInformation":{},"aggression":{},"evGain":{},"levelMoves":{"66":["Flare Blitz"],"1":["String Shot","Ember"],"12":["Struggle Bug"],"24":["Bug Bite"],"36":["Leech Life"],"48":["Take Down"],"6":["Flame Charge"],"18":["Flame Wheel"],"60":["Double-Edge"],"30":["Screech"],"42":["Bug Buzz"],"54":["Amnesia"]},"moves":{"egg":["Absorb","Harden","Thrash"],"evolution":[],"tr":["Giga Drain","Snore","Facade","Flamethrower","Leech Life","Light Screen","Overheat","U-turn","Solar Beam","Screech","Rest","Bug Buzz","Round","Heat Wave","Amnesia","Substitute","Acrobatics","Attract","Safeguard","Protect","Wild Charge","Sunny Day","Will-O-Wisp","Flare Blitz","Calm Mind","Psychic","Endure","Sleep Talk","Zen Headbutt","Fire Blast"]},"tutorMoves":{"Regular":["Skitter Smack"],"Transfer":["Secret Power","Morning Sun","Confide","Incinerate","Hidden Power","Magnet Rise","Double Team","Toxic","Swagger","Signal Beam","Return","Frustration","Foresight"]},"evolutions":[],"types":["Bug","Fire"],"canFly":false,"canSurf":false,"doesHover":false,"isRideable":false,"legendary":false,"expGainSpeed":72}