{"specialAttack":65,"specialDefense":100,"attack":105,"defense":75,"speed":50,"hp":105,"baseFriendship":70,"baseExp":157,"catchRate":75,"maleRatio":50,"pokedexId":89,"width":0.99,"height":0.99,"length":0.99,"weight":52.0,"minSpawnGroupSize":1,"maxSpawnGroupSize":1,"renderScale":[0.0,0.0,0.0],"guiScale":[1.0,1.0,1.0],"hoveringHeight":0,"eggCycles":20,"spawnInformation":{},"aggression":{},"evGain":{},"levelMoves":{"12":["Minimize","Disable"],"46":["Acid Armor"],"24":["Bite"],"57":["Memento"],"36":["Crunch"],"37":["Screech"],"15":["Acid Spray"],"48":["Acid Armor"],"26":["Fling"],"18":["Poison Fang","Disable"],"29":["Knock Off"],"1":["Venom Drench","Haze","Minimize","Bite","Pound","Harden","Poison Gas","Moonblast"],"4":["Harden"],"6":["Harden"],"7":["Bite"],"60":["Sludge Bomb"],"40":["Gunk Shot"],"52":["Belch"],"30":["Screech"],"32":["Crunch"],"21":["Minimize"]},"moves":{"egg":["Assurance","Pursuit","Shadow Sneak","Power-Up Punch","Spit Up","Curse","Clear Smog","Scary Face","Swallow","Spite","Imprison","Stockpile","Mean Look"],"evolution":[],"tr":["Fire Punch","Ice Punch","Thunder Punch","Hyper Beam","Giga Impact","Dig","Screech","Self-destruct","Rest","Rock Slide","Thief","Snore","Protect","Scary Face","Giga Drain","Attract","Rain Dance","Sunny Day","Facade","Swift","Helping Hand","Brick Break","Imprison","Rock Tomb","Mud Shot","Payback","Assurance","Fling","Venoshock","Round","Snarl","Brutal Swing","Body Slam","Flamethrower","Thunderbolt","Thunder","Fire Blast","Substitute","Sludge Bomb","Endure","Sleep Talk","Crunch","Shadow Ball","Taunt","Poison Jab","Dark Pulse","Focus Blast","Gunk Shot","Stone Edge","Sludge Wave","Venom Drench"]},"tutorMoves":{"Regular":["Giga Drain","Focus Punch","Snore","Knock Off","Recycle","Block","Pain Split","Spite","Gastro Acid","Gunk Shot","Shock Wave","Thunder Punch","Fire Punch","Ice Punch"],"Transfer":["Confide","Quash","Hidden Power","Self-Destruct","Double Team","Infestation","Headbutt","Swagger","Rock Polish","Torment","Frustration","Explosion","Mega Drain","Toxic","Embargo","Return","Foul Play"]},"evolutions":[],"types":["Poison","Dark"],"canFly":false,"canSurf":false,"doesHover":false,"isRideable":false,"legendary":false,"expGainSpeed":157}