{"specialAttack":127,"specialDefense":131,"attack":53,"defense":47,"speed":103,"hp":109,"baseFriendship":0,"baseExp":257,"catchRate":45,"maleRatio":-1,"pokedexId":793,"width":1.0,"height":1.0,"length":1.0,"weight":55.5,"minSpawnGroupSize":1,"maxSpawnGroupSize":1,"renderScale":[0.0,0.0,0.0],"guiScale":[0.0,0.0,0.0],"hoveringHeight":0,"eggCycles":120,"spawnInformation":{},"aggression":{},"evGain":{},"levelMoves":{},"moves":{},"tutorMoves":{},"evolutions":[],"types":["Rock","Poison"],"canFly":false,"canSurf":false,"doesHover":false,"isRideable":false,"legendary":false,"expGainSpeed":257}