{"specialAttack":40,"specialDefense":40,"attack":60,"defense":60,"speed":40,"hp":90,"baseFriendship":70,"baseExp":124,"catchRate":120,"maleRatio":50,"pokedexId":231,"width":0.7,"height":0.5,"length":0.7,"weight":33.5,"minSpawnGroupSize":1,"maxSpawnGroupSize":4,"renderScale":[0.0,0.0,0.0],"guiScale":[1.0,1.0,1.0],"hoveringHeight":0,"eggCycles":21,"spawnInformation":{},"aggression":{},"evGain":{},"levelMoves":{"33":["Charm"],"1":["Tackle","Odor Sleuth","Growl","Defense Curl"],"24":["Slam"],"37":["Last Resort"],"15":["Natural Gift"],"6":["Flail"],"28":["Take Down"],"19":["Endure"],"42":["Double-Edge"],"10":["Rollout"]},"moves":{"egg":["Mud-Slap","Endeavor","Snore","Heavy Slam","Ice Shard","High Horsepower","Focus Energy","Play Rough","Ancient Power","Fissure","Counter","Head Smash","Body Slam"],"evolution":[],"tr":["Rest","Rock Slide","Snore","Protect","Charm","Attract","Sandstorm","Sunny Day","Facade","Rock Tomb","Sand Tomb","Round","Bulldoze","Body Slam","Earthquake","Focus Energy","Substitute","Endure","Sleep Talk","Encore","Iron Tail","Superpower","Hyper Voice","Seed Bomb","Earth Power","Gunk Shot","Stealth Rock","Heavy Slam","Play Rough","High Horsepower"]},"tutorMoves":{"Regular":["Endeavor","Last Resort","Seed Bomb","Snore","Iron Tail","Stealth Rock","Earth Power","Knock Off","Superpower","Gunk Shot","Hyper Voice"],"Transfer":["Rock Smash","Secret Power","Confide","Curse","Hidden Power","Echoed Voice","Double Team","Toxic","Headbutt","Swagger","Water Gun","Return","Mimic","Captivate","Roar","Strength","Frustration"]},"evolutions":[],"types":["Ground"],"canFly":false,"canSurf":false,"doesHover":false,"isRideable":false,"legendary":false,"expGainSpeed":124}