{"specialAttack":50,"specialDefense":50,"attack":60,"defense":55,"speed":71,"hp":63,"baseFriendship":70,"baseExp":122,"catchRate":120,"maleRatio":50,"pokedexId":17,"width":0.7,"height":1.1,"length":0.7,"weight":30.0,"minSpawnGroupSize":1,"maxSpawnGroupSize":1,"renderScale":[0.0,0.0,0.0],"guiScale":[1.0,1.0,1.0],"hoveringHeight":0,"eggCycles":16,"spawnInformation":{},"aggression":{},"evGain":{},"levelMoves":{"11":["Mirror Move"],"22":["Twister"],"45":["Razor Wind"],"13":["Quick Attack"],"57":["Air Slash"],"47":["Tailwind"],"25":["Whirlwind"],"37":["Wing Attack"],"15":["Wing Attack"],"27":["Feather Dance"],"39":["Air Slash"],"17":["Roost","Whirlwind"],"1":["Quick Attack","Tackle","Sand Attack","Gust"],"3":["Sand Attack"],"5":["Sand Attack","Gust"],"9":["Quick Attack","Gust"],"62":["Hurricane"],"52":["Mirror Move"],"42":["Roost"],"31":["Agility"],"32":["Agility"]},"moves":{"egg":["Defog","Faint Attack","Uproar","Air Cutter","Steel Wing","Air Slash","Brave Bird","Pursuit","Foresight"],"evolution":[],"tr":["Fly","Rest","Thief","Snore","Protect","Steel Wing","Attract","Rain Dance","Sunny Day","Facade","U-turn","Round","Air Slash","Agility","Substitute","Endure","Sleep Talk","Uproar","Heat Wave","Brave Bird","Work Up","Hurricane"]},"tutorMoves":{"Regular":["Defog","Snore","Uproar","Sky Attack","Heat Wave","Tailwind"],"Transfer":["Ominous Wind","Secret Power","Detect","Natural Gift","Confide","Curse","Pluck","Double-Edge","Take Down","Hidden Power","Bide","Double Team","Swift","Mud-Slap","Toxic","Aerial Ace","Rage","Headbutt","Swagger","Return","Mimic","Captivate","Reflect","Frustration"]},"evolutions":[],"types":["Normal","Flying"],"canFly":true,"canSurf":false,"doesHover":false,"isRideable":false,"legendary":false,"expGainSpeed":122}