{"specialAttack":45,"specialDefense":35,"attack":25,"defense":25,"speed":40,"hp":28,"baseFriendship":35,"baseExp":70,"catchRate":235,"maleRatio":50,"pokedexId":280,"width":0.7,"height":0.4,"length":0.7,"weight":6.6,"minSpawnGroupSize":1,"maxSpawnGroupSize":4,"renderScale":[0.0,0.0,0.0],"guiScale":[1.0,1.0,1.0],"hoveringHeight":0,"eggCycles":21,"spawnInformation":{},"aggression":{},"evGain":{},"levelMoves":{"33":["Heal Pulse"],"12":["Draining Kiss"],"24":["Charm"],"36":["Dream Eater"],"15":["Teleport"],"27":["Calm Mind"],"39":["Future Sight"],"18":["Psybeam"],"1":["Disarming Voice","Growl"],"3":["Double Team"],"6":["Confusion"],"9":["Hypnosis"],"30":["Psychic"],"21":["Life Dew"]},"moves":{"egg":["Destiny Bond","Memento","Knock Off","Confuse Ray","Shadow Sneak","Grudge","Disable","Mean Look"],"evolution":[],"tr":["Taunt","Dazzling Gleam","Light Screen","Icy Wind","Magical Leaf","Encore","Wonder Room","Body Slam","Imprison","Substitute","Attract","Thunder Wave","Future Sight","Mega Punch","Sunny Day","Calm Mind","Fling","Endure","Swift","Zen Headbutt","Thunder Punch","Draining Kiss","Fire Punch","Ice Punch","Trick Room","Snore","Facade","Magic Room","Grass Knot","Mega Kick","Stored Power","Rest","Charm","Round","Misty Terrain","Shadow Ball","Skill Swap","Ally Switch","Hyper Voice","Helping Hand","Safeguard","Protect","Rain Dance","Thief","Psyshock","Trick","Will-O-Wisp","Psychic","Reflect","Sleep Talk","Thunderbolt"]},"tutorMoves":{"Regular":["Expanding Force"],"Transfer":["Snatch","Natural Gift","Confide","Double-Edge","Hidden Power","Synchronoise","Shock Wave","Telekinesis","Headbutt","Swagger","Charge Beam","Defense Curl","Mimic","Captivate","Torment","Frustration","Secret Power","Psych Up","Magic Coat","Lucky Chant","Echoed Voice","Recycle","Mud-Slap","Toxic","Pain Split","Flash","Signal Beam","Return"]},"evolutions":[],"types":["Psychic","Fairy"],"canFly":false,"canSurf":false,"doesHover":false,"isRideable":false,"legendary":false,"expGainSpeed":70}