{"specialAttack":30,"specialDefense":30,"attack":40,"defense":50,"speed":30,"hp":40,"baseFriendship":70,"baseExp":74,"catchRate":255,"maleRatio":50,"pokedexId":273,"width":0.7,"height":0.5,"length":0.7,"weight":4.0,"minSpawnGroupSize":1,"maxSpawnGroupSize":4,"renderScale":[0.0,0.0,0.0],"guiScale":[1.0,1.0,1.0],"hoveringHeight":0,"eggCycles":16,"spawnInformation":{},"aggression":{},"evGain":{},"levelMoves":{"33":["Explosion"],"1":["Tackle","Harden"],"12":["Rollout"],"24":["Sunny Day"],"3":["Absorb"],"15":["Mega Drain"],"27":["Synthesis"],"6":["Astonish"],"18":["Payback"],"9":["Growth"],"30":["Sucker Punch"],"21":["Nature Power"]},"moves":{"egg":["Defog","Quick Attack","Worry Seed","Take Down","Night Slash","Leech Seed"],"evolution":[],"tr":["Giga Drain","Snore","Facade","Beat Up","Grass Knot","Retaliate","Swords Dance","Solar Beam","Rest","Seed Bomb","Nasty Plot","Bullet Seed","Round","Body Slam","Shadow Ball","Amnesia","Grassy Terrain","Substitute","Power Swap","Attract","Payback","Energy Ball","False Swipe","Protect","Dig","Self-Destruct","Sunny Day","Foul Play","Endure","Sleep Talk"]},"tutorMoves":{"Regular":["Grassy Glide"],"Transfer":["Rock Smash","Secret Power","Natural Gift","Confide","Double-Edge","Hidden Power","Bide","Double Team","Spite","Toxic","Headbutt","Razor Wind","Swagger","Defense Curl","Flash","Return","Mimic","Captivate","Frustration"]},"evolutions":[],"types":["Grass"],"canFly":false,"canSurf":false,"doesHover":false,"isRideable":false,"legendary":false,"expGainSpeed":74}