{"specialAttack":42,"specialDefense":88,"attack":42,"defense":118,"speed":30,"hp":30,"baseFriendship":70,"baseExp":99,"catchRate":45,"maleRatio":87,"pokedexId":410,"width":0.5,"height":0.5,"length":0.5,"weight":57.0,"minSpawnGroupSize":1,"maxSpawnGroupSize":1,"renderScale":[0.0,0.0,0.0],"guiScale":[0.0,0.0,0.0],"hoveringHeight":0,"eggCycles":31,"spawnInformation":{},"aggression":{},"evGain":{},"levelMoves":{},"moves":{},"tutorMoves":{},"evolutions":[],"types":["Rock","Steel"],"canFly":false,"canSurf":false,"doesHover":false,"isRideable":false,"legendary":false,"expGainSpeed":99}