{"specialAttack":40,"specialDefense":60,"attack":40,"defense":60,"speed":35,"hp":60,"baseFriendship":70,"baseExp":65,"catchRate":255,"maleRatio":50,"pokedexId":285,"width":0.7,"height":0.4,"length":0.7,"weight":4.5,"minSpawnGroupSize":1,"maxSpawnGroupSize":4,"renderScale":[0.0,0.0,0.0],"guiScale":[1.0,1.0,1.0],"hoveringHeight":0,"eggCycles":16,"spawnInformation":{},"aggression":{},"evGain":{},"levelMoves":{"33":["Toxic"],"22":["Worry Seed"],"1":["Tackle","Absorb"],"12":["Mega Drain"],"36":["Seed Bomb"],"26":["Giga Drain"],"15":["Headbutt"],"5":["Stun Spore"],"29":["Growth"],"19":["Poison Powder"],"8":["Leech Seed"],"40":["Spore"]},"moves":{"egg":["Helping Hand","Focus Punch","Drain Punch","Seed Bomb","Worry Seed","Fake Tears","Charm","Bullet Seed","Wake-Up Slap","Natural Gift"],"evolution":[],"tr":["Solar Beam","Safeguard","Rest","Snore","Protect","Giga Drain","Charm","Attract","Sunny Day","Facade","Swift","Helping Hand","Fake Tears","Bullet Seed","Drain Punch","Venoshock","Round","False Swipe","Body Slam","Substitute","Sludge Bomb","Endure","Sleep Talk","Seed Bomb","Energy Ball","Grass Knot"]},"tutorMoves":{"Regular":["Giga Drain","Helping Hand","Focus Punch","Drain Punch","Seed Bomb","Snore","Worry Seed","Synthesis","Snatch"],"Transfer":["Secret Power","Swords Dance","Confide","Double-Edge","Hidden Power","Double Team","Swagger","Flash","Return","Mimic","Captivate","Frustration"]},"evolutions":[],"types":["Grass"],"canFly":false,"canSurf":false,"doesHover":false,"isRideable":false,"legendary":false,"expGainSpeed":65}