{"specialAttack":59,"specialDefense":57,"attack":48,"defense":66,"speed":49,"hp":62,"baseFriendship":0,"baseExp":68,"catchRate":200,"maleRatio":50,"pokedexId":684,"width":0.4,"height":0.4,"length":0.4,"weight":3.5,"minSpawnGroupSize":1,"maxSpawnGroupSize":1,"renderScale":[0.0,0.0,0.0],"guiScale":[1.0,1.0,1.0],"hoveringHeight":0,"eggCycles":21,"spawnInformation":{},"aggression":{},"evGain":{},"levelMoves":{"33":["Play Rough"],"12":["Draining Kiss"],"24":["Cotton Spore"],"36":["Cotton Guard"],"15":["Fake Tears"],"27":["Energy Ball"],"39":["Endeavor"],"18":["Round"],"1":["Tackle","Sweet Scent"],"3":["Play Nice"],"6":["Fairy Wind"],"9":["Aromatherapy"],"30":["Wish"],"21":["String Shot"]},"moves":{"egg":["After You","Yawn","Sticky Web","Copycat"],"evolution":[],"tr":["Snore","Facade","Flamethrower","Play Rough","Dazzling Gleam","Light Screen","Surf","Rest","Charm","Round","Amnesia","Substitute","Attract","Helping Hand","Energy Ball","Safeguard","Protect","Rain Dance","Thief","Fake Tears","Sunny Day","Calm Mind","Psychic","Endure","Sleep Talk","Thunderbolt","Draining Kiss"]},"tutorMoves":{"Regular":["Misty Explosion"],"Transfer":["Secret Power","Psych Up","Dream Eater","Confide","Belly Drum","Hidden Power","Magic Coat","Double Team","Heal Bell","Toxic","Swagger","Flash","Return","Gastro Acid","Covet","Frustration"]},"evolutions":[],"types":["Fairy"],"canFly":false,"canSurf":false,"doesHover":false,"isRideable":false,"legendary":false,"expGainSpeed":68}